trifold/__init__.py
trifold/__main__.py
trifold/py.typed
trifold-0.3.0.dist-info/licenses/LICENSE
trifold-0.3.0.dist-info/METADATA
trifold-0.3.0.dist-info/WHEEL
trifold-0.3.0.dist-info/entry_points.txt
trifold-0.3.0.dist-info/top_level.txt
trifold-0.3.0.dist-info/RECORD
