Metadata-Version: 2.4
Name: trifold
Version: 0.3.0
Summary: A quick way to deploy static websites to a fast, cheap, and reliable CDN.
Author-email: jpt <dev@jpt.sh>
License-Expression: AGPL-3.0-or-later
Project-URL: Repository, https://codeberg.org/jpt/trifold.git
Requires-Python: >=3.13
License-File: LICENSE
Requires-Dist: httpx>=0.28.1
Requires-Dist: rich>=14.2.0
Requires-Dist: typer>=0.20.0
Dynamic: license-file
